pypi_json/typehints.py
pypi_json/py.typed
pypi_json/__init__.py
pypi_json-0.2.1.dist-info/LICENSE
pypi_json-0.2.1.dist-info/METADATA
pypi_json-0.2.1.dist-info/top_level.txt
pypi_json-0.2.1.dist-info/entry_points.txt
pypi_json-0.2.1.dist-info/WHEEL
pypi_json-0.2.1.dist-info/RECORD
