Metadata-Version: 2.1
Name: pypi-json
Version: 0.2.1
Summary: PyPI JSON API client library
Author-email: Dominic Davis-Foster <dominic@davis-foster.co.uk>
License: MIT
Keywords: json,packaging,pypi,warehouse
Home-page: https://github.com/repo-helper/pypi-json
Project-URL: Issue Tracker, https://github.com/repo-helper/pypi-json/issues
Project-URL: Source Code, https://github.com/repo-helper/pypi-json
Project-URL: Documentation, https://pypi-json.readthedocs.io/en/latest
Platform: Windows
Platform: macOS
Platform: Linux
Classifier: Development Status :: 4 - Beta
Classifier: Intended Audience :: Developers
Classifier: License :: OSI Approved :: MIT License
Classifier: Operating System :: OS Independent
Classifier: Programming Language :: Python
Classifier: Programming Language :: Python :: 3 :: Only
Classifier: Programming Language :: Python :: 3.6
Classifier: Programming Language :: Python :: 3.7
Classifier: Programming Language :: Python :: 3.8
Classifier: Programming Language :: Python :: 3.9
Classifier: Programming Language :: Python :: 3.10
Classifier: Programming Language :: Python :: Implementation :: CPython
Classifier: Programming Language :: Python :: Implementation :: PyPy
Classifier: Topic :: Software Development :: Libraries :: Python Modules
Classifier: Typing :: Typed
Requires-Python: >=3.6
Requires-Dist: apeye>=1.1.0
Requires-Dist: packaging>=21.0
Requires-Dist: requests>=2.26.0
